streamlit_folder_upload/__init__.py
streamlit_folder_upload/frontend/build/asset-manifest.json
streamlit_folder_upload/frontend/build/bootstrap.min.css
streamlit_folder_upload/frontend/build/index.html
streamlit_folder_upload/frontend/build/static/css/2.f4c5cc59.chunk.css
streamlit_folder_upload/frontend/build/static/css/2.f4c5cc59.chunk.css.map
streamlit_folder_upload/frontend/build/static/js/2.24a0d854.chunk.js
streamlit_folder_upload/frontend/build/static/js/2.24a0d854.chunk.js.LICENSE.txt
streamlit_folder_upload/frontend/build/static/js/2.24a0d854.chunk.js.map
streamlit_folder_upload/frontend/build/static/js/main.da33716a.chunk.js
streamlit_folder_upload/frontend/build/static/js/main.da33716a.chunk.js.map
streamlit_folder_upload/frontend/build/static/js/runtime-main.e6b0ae4c.js
streamlit_folder_upload/frontend/build/static/js/runtime-main.e6b0ae4c.js.map
streamlit_folder_upload-0.0.1.dist-info/LICENSE
streamlit_folder_upload-0.0.1.dist-info/METADATA
streamlit_folder_upload-0.0.1.dist-info/WHEEL
streamlit_folder_upload-0.0.1.dist-info/top_level.txt
streamlit_folder_upload-0.0.1.dist-info/RECORD
